blockmodelbackend/__init__.py
blockmodelbackend/apps.py
blockmodelbackend/modelbackend.py
blockmodelbackend/models.py
blockmodelbackend/migrations/0001_initial.py
blockmodelbackend/migrations/__init__.py
django_blockmodelbackend-0.3.0.dist-info/LICENSE
django_blockmodelbackend-0.3.0.dist-info/METADATA
django_blockmodelbackend-0.3.0.dist-info/WHEEL
django_blockmodelbackend-0.3.0.dist-info/top_level.txt
django_blockmodelbackend-0.3.0.dist-info/RECORD
