Metadata-Version: 2.1
Name: django-blockmodelbackend
Version: 0.3.0
Summary: Custom model backend for blocking users and ip after several attempts to access wrongly
Home-page: https://github.com/JavierGonza/django-blockmodelbackend
Author: Javier González
Author-email: correo@javier-gonzalez.es
License: MIT
Keywords: django-blockmodelbackend
Platform: UNKNOWN
Classifier: Intended Audience :: Developers
Classifier: Programming Language :: Python :: 2
Classifier: Programming Language :: Python :: 2.7
Classifier: Programming Language :: Python :: 3
Classifier: Programming Language :: Python :: 3.4
Classifier: Programming Language :: Python :: 3.5
Classifier: Programming Language :: Python :: 3.6
Classifier: Framework :: Django
Classifier: Framework :: Django :: 1.8
Classifier: Framework :: Django :: 1.9
Classifier: Framework :: Django :: 1.10
Classifier: Framework :: Django :: 1.11
Classifier: Development Status :: 4 - Beta
Classifier: License :: OSI Approved :: MIT License
Requires-Dist: Django (<2.3,>=1.11)
Requires-Dist: django-ipware (==2.1.0)
